{"createDate":"2025-02-26T12:21:26.285Z","updateDate":"2025-02-26T12:21:54.369Z","uuid":"f24b3eb3-7e57-4592-bde7-6253d8cc8e9c","hash":"","name":"Generic Document Review","description":"Can be used to review any document.","entity":"VC","documentFileId":"67bf076292ad65ff7ca2e0aa","contextFileId":"67bf076292ad65ff7ca2e0ac","version":"5.0.0","sourceVersion":"","creator":"did:hedera:testnet:8WugXWGzf7gKaLRXfBiZNLzzUrhqMPBRUR7Rf6nhAWGE_0.0.5622502","owner":"did:hedera:testnet:8WugXWGzf7gKaLRXfBiZNLzzUrhqMPBRUR7Rf6nhAWGE_0.0.5622502","topicId":"0.0.5622540","messageId":"1740572511.757133911","documentURL":"ipfs://bafybeidrmopcqbzvyzuw7vcw5qnszxehu4txipyhpmqyxffjbvz5oidjsm","contextURL":"ipfs://bafybeih6tg7qoinhhvfrrig7njipek6d33wueawzdvvzblj5j7qjcuh6lq","iri":"#f24b3eb3-7e57-4592-bde7-6253d8cc8e9c&5.0.0","system":false,"active":false,"category":"POLICY","codeVersion":"1.1.0","defs":["#d4713b72-e2bf-47ee-a0a9-d2d56c06ff1b&1.0.0","#1b14bff4-b6e7-416b-992e-866c1b658f35&1.0.0"],"errors":[],"document":{"$id":"#f24b3eb3-7e57-4592-bde7-6253d8cc8e9c&5.0.0","$comment":"{ \"@id\": \"ipfs://bafybeih6tg7qoinhhvfrrig7njipek6d33wueawzdvvzblj5j7qjcuh6lq#f24b3eb3-7e57-4592-bde7-6253d8cc8e9c&5.0.0\", \"term\": \"f24b3eb3-7e57-4592-bde7-6253d8cc8e9c&5.0.0\", \"previousVersion\": \"4.0.0\" }","title":"Generic Document Review","description":"Can be used to review any document.","type":"object","properties":{"@context":{"oneOf":[{"type":"string"},{"type":"array","items":{"type":"string"}}],"readOnly":true},"type":{"oneOf":[{"type":"string"},{"type":"array","items":{"type":"string"}}],"readOnly":true},"id":{"type":"string","readOnly":true},"headers":{"title":"Headers","description":"Document headers:","readOnly":false,"$ref":"#d4713b72-e2bf-47ee-a0a9-d2d56c06ff1b&1.0.0","$comment":"{\"term\":\"headers\",\"@id\":\"ipfs://bafybeih6tg7qoinhhvfrrig7njipek6d33wueawzdvvzblj5j7qjcuh6lq#d4713b72-e2bf-47ee-a0a9-d2d56c06ff1b&1.0.0\",\"orderPosition\":0}"},"policyId":{"title":"policyId","description":"policyId","readOnly":true,"type":"string","$comment":"{\"term\":\"policyId\",\"@id\":\"https://www.schema.org/text\"}"},"ref":{"title":"ref","description":"ref","readOnly":true,"type":"string","$comment":"{\"term\":\"ref\",\"@id\":\"https://www.schema.org/text\"}"},"review":{"title":"Review","description":"Review:","readOnly":false,"type":"array","items":{"$ref":"#1b14bff4-b6e7-416b-992e-866c1b658f35&1.0.0"},"$comment":"{\"term\":\"review\",\"@id\":\"ipfs://bafybeih6tg7qoinhhvfrrig7njipek6d33wueawzdvvzblj5j7qjcuh6lq#1b14bff4-b6e7-416b-992e-866c1b658f35&1.0.0\",\"orderPosition\":1}"},"final_rd":{"title":"Final Reviewer Decision","description":"(Calculated internally)","readOnly":false,"type":"string","enum":["APPROVE","REJECT"],"$comment":"{\"term\":\"final_rd\",\"@id\":\"https://www.schema.org/text\",\"customType\":\"enum\",\"orderPosition\":2}"}},"required":["@context","type","headers","policyId","review","final_rd"],"additionalProperties":false,"$defs":{"#d4713b72-e2bf-47ee-a0a9-d2d56c06ff1b&1.0.0":{"$id":"#d4713b72-e2bf-47ee-a0a9-d2d56c06ff1b&1.0.0","$comment":"{ \"@id\": \"ipfs://bafybeiacel2ouyqteshwyditeujrokabrbs2ehlowh3ikekupr5iqdmgvy#d4713b72-e2bf-47ee-a0a9-d2d56c06ff1b&1.0.0\", \"term\": \"d4713b72-e2bf-47ee-a0a9-d2d56c06ff1b&1.0.0\" }","title":"Document Headers","description":"Captures information about the document's predecessor and submittor.","type":"object","properties":{"@context":{"oneOf":[{"type":"string"},{"type":"array","items":{"type":"string"}}],"readOnly":true},"type":{"oneOf":[{"type":"string"},{"type":"array","items":{"type":"string"}}],"readOnly":true},"id":{"type":"string","readOnly":true},"id_msg_pred":{"title":"Message ID of Predecessor","description":"Message ID of the document that preceded this document:","readOnly":false,"type":"string","$comment":"{\"term\":\"id_msg_pred\",\"@id\":\"https://www.schema.org/text\",\"orderPosition\":0}"},"policyId":{"title":"policyId","description":"policyId","readOnly":true,"type":"string","$comment":"{\"term\":\"policyId\",\"@id\":\"https://www.schema.org/text\"}"},"ref":{"title":"ref","description":"ref","readOnly":true,"type":"string","$comment":"{\"term\":\"ref\",\"@id\":\"https://www.schema.org/text\"}"},"url_ipfs_pred":{"title":"IPFS URL of Predecessor","description":"IPFS URL of the document that preceded this document:","readOnly":false,"type":"string","$comment":"{\"term\":\"url_ipfs_pred\",\"@id\":\"https://www.schema.org/text\",\"orderPosition\":1}"},"id_msg_lic":{"title":"Message ID of Submittor License","description":"Message ID of the relevant license of the submittor of this document:","readOnly":false,"type":"string","$comment":"{\"term\":\"id_msg_lic\",\"@id\":\"https://www.schema.org/text\",\"orderPosition\":2}"},"url_ipfs_lic":{"title":"IPFS URL of Submittor License","description":"IPFS URL of the relevant license of the submittor of this document:","readOnly":false,"type":"string","$comment":"{\"term\":\"url_ipfs_lic\",\"@id\":\"https://www.schema.org/text\",\"orderPosition\":3}"},"id_subject":{"title":"Subject ID","description":"ID of the subject of this document (e.g., project ID or agent ID):","readOnly":false,"type":"string","$comment":"{\"term\":\"id_subject\",\"@id\":\"https://www.schema.org/text\",\"orderPosition\":4}"},"type_subject":{"title":"Subject Type","description":"Type of the subject of this document:","readOnly":false,"type":"string","enum":["PROJECT","AGENT"],"$comment":"{\"term\":\"type_subject\",\"@id\":\"https://www.schema.org/text\",\"customType\":\"enum\",\"orderPosition\":5}"}},"required":["@context","type","policyId"],"additionalProperties":false},"#1b14bff4-b6e7-416b-992e-866c1b658f35&1.0.0":{"$id":"#1b14bff4-b6e7-416b-992e-866c1b658f35&1.0.0","$comment":"{ \"@id\": \"ipfs://bafybeicymajn33prhwc5x6lhsboma2bj2aijb25t4csi2rdlc2wcyymjji#1b14bff4-b6e7-416b-992e-866c1b658f35&1.0.0\", \"term\": \"1b14bff4-b6e7-416b-992e-866c1b658f35&1.0.0\" }","title":"Document Field Review","description":"Used to review a single field of a document.","type":"object","properties":{"@context":{"oneOf":[{"type":"string"},{"type":"array","items":{"type":"string"}}],"readOnly":true},"type":{"oneOf":[{"type":"string"},{"type":"array","items":{"type":"string"}}],"readOnly":true},"id":{"type":"string","readOnly":true},"field_key":{"title":"Field Key","description":"Key of the document field under review:","readOnly":false,"type":"string","$comment":"{\"term\":\"field_key\",\"@id\":\"https://www.schema.org/text\",\"orderPosition\":0}"},"policyId":{"title":"policyId","description":"policyId","readOnly":true,"type":"string","$comment":"{\"term\":\"policyId\",\"@id\":\"https://www.schema.org/text\"}"},"ref":{"title":"ref","description":"ref","readOnly":true,"type":"string","$comment":"{\"term\":\"ref\",\"@id\":\"https://www.schema.org/text\"}"},"field_title":{"title":"Field Title","description":"Title of the document field under review:","readOnly":false,"type":"string","$comment":"{\"term\":\"field_title\",\"@id\":\"https://www.schema.org/text\",\"orderPosition\":1}"},"field_prompt":{"title":"Field Prompt","description":"Original prompt to the document field under review:","readOnly":false,"type":"string","$comment":"{\"term\":\"field_prompt\",\"@id\":\"https://www.schema.org/text\",\"orderPosition\":2}"},"original_response":{"title":"Original Response","description":"Author's response to the document field under review:","readOnly":false,"type":"string","$comment":"{\"term\":\"original_response\",\"@id\":\"https://www.schema.org/text\",\"orderPosition\":3}"},"reviewer_decision":{"title":"Reviewer Decision","description":"Outcome of reviewer's evaluation of the author's response to the document field under review:","readOnly":false,"type":"string","enum":["APPROVE","FORWARD_ACTION_REQUEST","CORRECTIVE_ACTION_REQUEST","REJECT"],"$comment":"{\"term\":\"reviewer_decision\",\"@id\":\"https://www.schema.org/text\",\"customType\":\"enum\",\"orderPosition\":4}"},"reviewer_feedback":{"title":"Reviewer Feedback","description":"Reviewer's feedback on the author's response to the document field under review:","readOnly":false,"type":"string","$comment":"{\"term\":\"reviewer_feedback\",\"@id\":\"https://www.schema.org/text\",\"orderPosition\":5}"}},"required":["@context","type","field_key","policyId","field_title","field_prompt","original_response","reviewer_decision","reviewer_feedback"],"additionalProperties":false}}},"context":{"@context":{"@version":1.1,"@vocab":"https://w3id.org/traceability/#undefinedTerm","id":"@id","type":"@type","d4713b72-e2bf-47ee-a0a9-d2d56c06ff1b&1.0.0":{"@id":"ipfs://bafybeiacel2ouyqteshwyditeujrokabrbs2ehlowh3ikekupr5iqdmgvy#d4713b72-e2bf-47ee-a0a9-d2d56c06ff1b&1.0.0","@context":{"id_msg_pred":{"@type":"https://www.schema.org/text"},"policyId":{"@type":"https://www.schema.org/text"},"ref":{"@type":"https://www.schema.org/text"},"url_ipfs_pred":{"@type":"https://www.schema.org/text"},"id_msg_lic":{"@type":"https://www.schema.org/text"},"url_ipfs_lic":{"@type":"https://www.schema.org/text"},"id_subject":{"@type":"https://www.schema.org/text"},"type_subject":{"@type":"https://www.schema.org/text"}}},"1b14bff4-b6e7-416b-992e-866c1b658f35&1.0.0":{"@id":"ipfs://bafybeicymajn33prhwc5x6lhsboma2bj2aijb25t4csi2rdlc2wcyymjji#1b14bff4-b6e7-416b-992e-866c1b658f35&1.0.0","@context":{"field_key":{"@type":"https://www.schema.org/text"},"policyId":{"@type":"https://www.schema.org/text"},"ref":{"@type":"https://www.schema.org/text"},"field_title":{"@type":"https://www.schema.org/text"},"field_prompt":{"@type":"https://www.schema.org/text"},"original_response":{"@type":"https://www.schema.org/text"},"reviewer_decision":{"@type":"https://www.schema.org/text"},"reviewer_feedback":{"@type":"https://www.schema.org/text"}}},"f24b3eb3-7e57-4592-bde7-6253d8cc8e9c&5.0.0":{"@id":"schema:f24b3eb3-7e57-4592-bde7-6253d8cc8e9c#f24b3eb3-7e57-4592-bde7-6253d8cc8e9c&5.0.0","@context":{"headers":{"@id":"ipfs://bafybeifqbkwns7mhhmewxbywskdnrtddgkxl2evqbgrupojrrkgnf5ktkq#d4713b72-e2bf-47ee-a0a9-d2d56c06ff1b&1.0.0"},"review":{"@id":"ipfs://bafybeifqbkwns7mhhmewxbywskdnrtddgkxl2evqbgrupojrrkgnf5ktkq#1b14bff4-b6e7-416b-992e-866c1b658f35&1.0.0"},"final_rd":{"@type":"https://www.schema.org/text"},"policyId":{"@type":"https://www.schema.org/text"},"ref":{"@type":"https://www.schema.org/text"}}}}},"id":"67bf074392ad65ff7ca2e0a5"}